{
  "project_info": {
    "project_number": "444851730450",
    "project_id": "college-saathi-adshed",
    "storage_bucket": "college-saathi-adshed.appspot.com"
  },
  "client": [
    {
      "client_info": {
        "mobilesdk_app_id": "1:444851730450:android:87020e9ad35302636080cb",
        "android_client_info": {
          "package_name": "com.example.college_saathi"
        }
      },
      "oauth_client": [
        {
          "client_id": "444851730450-tkejqu77vce720nc1kuojqb1bn54t9n0.apps.googleusercontent.com",
          "client_type": 3
        }
      ],
      "api_key": [
        {
          "current_key": "AIzaSyBJHIGdLZRhfEqoUmdghKm-v7-sB3mS7wk"
        }
      ],
      "services": {
        "appinvite_service": {
          "other_platform_oauth_client": [
            {
              "client_id": "444851730450-tkejqu77vce720nc1kuojqb1bn54t9n0.apps.googleusercontent.com",
              "client_type": 3
            }
          ]
        }
      }
    }
  ],
  "configuration_version": "1"
}